spylunking/__init__.py
spylunking/consts.py
spylunking/ev.py
spylunking/get_session_key.py
spylunking/get_token.py
spylunking/mp_splunk_publisher.py
spylunking/ppj.py
spylunking/rnow.py
spylunking/search.py
spylunking/send_to_splunk.py
spylunking/socket_send.py
spylunking/splunk_publisher.py
spylunking/tcp_splunk_publisher.py
spylunking/wait_for_exit.py
spylunking/log/__init__.py
spylunking/log/setup_logging.py
spylunking/scripts/__init__.py
spylunking/scripts/get_splunk_token.py
spylunking/scripts/search_splunk.py
spylunking/scripts/show_service_token.py
spylunking/scripts/start_logging_loader.py
spylunking/scripts/test_logging.py
spylunking/scripts/test_publish_to_splunk.py
spylunking-1.2.10.data/scripts/get_splunk_token.py
spylunking-1.2.10.data/scripts/logs.sh
spylunking-1.2.10.data/scripts/search_splunk.py
spylunking-1.2.10.data/scripts/show_service_token.py
spylunking-1.2.10.data/scripts/sp
spylunking-1.2.10.data/scripts/start_logging_loader.py
spylunking-1.2.10.data/scripts/test_logging.py
spylunking-1.2.10.data/scripts/test_publish_to_splunk.py
spylunking-1.2.10.dist-info/LICENSE
spylunking-1.2.10.dist-info/METADATA
spylunking-1.2.10.dist-info/WHEEL
spylunking-1.2.10.dist-info/top_level.txt
spylunking-1.2.10.dist-info/RECORD
